{"owner": {"account_name": "remamsterdam", "head_block_num": 6630175, "head_block_time": "2019-12-13T08:38:45.500", "privileged": false, "last_code_update": "1970-01-01T00:00:00.000", "created": "2019-11-07T19:13:51.500", "core_liquid_balance": "0.0000 REM", "ram_quota": 17179869, "net_weight": 2500000000, "cpu_weight": 2500000000, "net_limit": {"used": 352, "available": "86425122529", "max": "86425122881"}, "cpu_limit": {"used": 5641, "available": "16484278355", "max": "16484283996"}, "ram_usage": 4316, "permissions": [{"perm_name": "active", "parent": "owner", "required_auth": {"threshold": 1, "keys": [{"key": "EOS6BiEPCQaugxDYfmUTTRNKb4UjmumHzGzT1LCA24x3jXDUP3j8z", "weight": 1}], "accounts": [], "waits": []}}, {"perm_name": "owner", "parent": "", "required_auth": {"threshold": 1, "keys": [{"key": "EOS6BiEPCQaugxDYfmUTTRNKb4UjmumHzGzT1LCA24x3jXDUP3j8z", "weight": 1}], "accounts": [], "waits": []}}], "total_resources": {"owner": "remamsterdam", "net_weight": "250000.0000 REM", "cpu_weight": "250000.0000 REM", "own_stake_amount": 2500000000, "free_stake_amount": 0}, "self_delegated_bandwidth": {"from": "remamsterdam", "to": "remamsterdam", "net_weight": "250000.0000 REM", "cpu_weight": "250000.0000 REM"}, "refund_request": null, "voter_info": {"owner": "remamsterdam", "proxy": "", "producers": ["remamsterdam"], "staked": 2500000000, "locked_stake": 2500000000, "last_vote_weight": "629145600000000.00000000000000000", "stake_lock_time": "2020-05-06T17:49:20.574", "last_undelegate_time": "1970-01-01T00:00:00.000", "proxied_vote_weight": "0.00000000000000000", "is_proxy": 0, "flags1": 0, "reserved2": 0, "reserved3": "0 ", "last_reassertion_time": "2019-12-11T18:28:59.000", "pending_perstake_reward": 85417648, "last_claim_time": "2019-12-11T18:27:48.500"}, "rex_info": null}, "bp.json": false, "locked_stake_total": 4722256022965}